{
  "openapi": "3.1.1",
  "info": {
    "title": "NoSQLinjection | v1",
    "version": "1.0.0"
  },
  "servers": [
    {
      "url": "http://localhost:5045"
    }
  ],
  "paths": {
    "/api/Auth/login": {
      "post": {
        "tags": [
          "Auth"
        ],
        "requestBody": {
          "content": {
            "application/json": {
              "schema": {
                "$ref": "#/components/schemas/JsonElement"
              }
            },
            "text/json": {
              "schema": {
                "$ref": "#/components/schemas/JsonElement"
              }
            },
            "application/*+json": {
              "schema": {
                "$ref": "#/components/schemas/JsonElement"
              }
            }
          },
          "required": true
        },
        "responses": {
          "200": {
            "description": "OK"
          }
        }
      }
    }
  },
  "components": {
    "schemas": {
      "JsonElement": { }
    }
  },
  "tags": [
    {
      "name": "Auth"
    }
  ]
}